{
  "filter": "Short play clips only; condensed games and full-game recaps excluded.",
  "game": {
    "date": "2026-05-18",
    "game_datetime": "2026-05-18T23:10:00Z",
    "game_pk": 824114,
    "home_away": "home",
    "matchup": "Royals vs Red Sox",
    "opponent": "Boston Red Sox",
    "probable_pitchers": {
      "opponent": {
        "id": 543243,
        "name": "Sonny Gray"
      },
      "royals": {
        "id": 607625,
        "name": "Seth Lugo"
      }
    },
    "recap_slug": "2026-05-18-royals-vs-red-sox",
    "result": "L",
    "score": "KC 1, BOS 3",
    "site": "Home",
    "venue": "Kauffman Stadium"
  },
  "generated_at": "2026-05-19T07:20:10.131539+00:00",
  "highlights": [
    {
      "date": "2026-05-19T03:21:58.799Z",
      "description": "Sonny Gray strikes out nine and Willson Contreras hits a two-run home run to fuel the Red Sox to a 3-1 win over the Royals",
      "duration": "00:03:29",
      "id": "sonny-gray-willson-contreras-lead-red-sox-to-3-1-win",
      "image_url": "https://img.mlbstatic.com/mlb-images/image/upload/w_1920,h_1080,f_jpg,c_fill,g_auto/mlb/c5n3ebujzrvglykf1kfw.jpg",
      "mlb_url": null,
      "playback_type": "mp4Avc",
      "playback_url": "https://mlb-cuts-diamond.mlb.com/FORGE/2026/2026-05/18/adb58dae-6607f743-14edc9d1-csvm-diamondgcp-asset_1280x720_59_4000K.mp4",
      "title": "Sonny Gray, Willson Contreras lead Red Sox to 3-1 win"
    },
    {
      "date": "2026-05-19T00:30:58.414Z",
      "description": "Willson Contreras breaks the scoreless tie with a two-run home run to left-center field in the top of the 6th",
      "duration": "00:00:28",
      "id": "seth-lugo-in-play-run-s-to-willson-contreras",
      "image_url": "https://img.mlbstatic.com/mlb-images/image/upload/w_1920,h_1080,f_jpg,c_fill,g_auto/mlb/eh7o5wa2dgzn2laqhgix.jpg",
      "mlb_url": null,
      "playback_type": "mp4Avc",
      "playback_url": "https://mlb-cuts-diamond.mlb.com/FORGE/2026/2026-05/18/f519aaa4-b8f64201-53b116a8-csvm-diamondgcp-asset_1280x720_59_4000K.mp4",
      "title": "Willson Contreras' two-run home run (10)"
    },
    {
      "date": "2026-05-19T05:07:45.099Z",
      "description": "Take a look at Willson Contreras' two-run homer through data visualization\\n",
      "duration": "00:00:30",
      "id": "data-viz-willson-contreras-home-run",
      "image_url": "https://img.mlbstatic.com/mlb-images/image/upload/w_1920,h_1080,f_jpg,c_fill,g_auto/mlb/z50w6dmqzhimqk26jft7.jpg",
      "mlb_url": null,
      "playback_type": "mp4Avc",
      "playback_url": "https://mlb-cuts-diamond.mlb.com/FORGE/2026/2026-05/18/834cc01f-d8af3c98-9903c8a2-csvm-diamondgcp-asset_1280x720_59_4000K.mp4",
      "title": "Data Viz: Willson Contreras' home run"
    },
    {
      "date": "2026-05-19T00:56:00.304Z",
      "description": "Jac Caglianone laces an RBI double to right-center field to cut the Royals' deficit to 3-1 in the 7th",
      "duration": "00:00:27",
      "id": "sonny-gray-in-play-run-s-to-jac-caglianone",
      "image_url": "https://img.mlbstatic.com/mlb-images/image/upload/w_1920,h_1080,f_jpg,c_fill,g_auto/v1779155476/mlb/zxpijrpfiuw77rbbakfh.jpg",
      "mlb_url": null,
      "playback_type": "mp4Avc",
      "playback_url": "https://mlb-cuts-diamond.mlb.com/FORGE/2026/2026-05/18/06b6b7f6-04f9db36-3671662d-csvm-diamondgcp-asset_1280x720_59_4000K.mp4",
      "title": "Jac Caglianone's RBI double"
    },
    {
      "date": "2026-05-19T01:30:10.952Z",
      "description": "Sonny Gray tallies nine strikeouts across six-plus innings of work in his start against the Royals to earn his fifth win of the season",
      "duration": "00:01:50",
      "id": "sonny-gray-s-nine-strikeouts-x7808",
      "image_url": "https://img.mlbstatic.com/mlb-images/image/upload/w_1920,h_1080,f_jpg,c_fill,g_auto/v1779156754/mlb/ww7jtkwxinkdedeekfct.jpg",
      "mlb_url": null,
      "playback_type": "mp4Avc",
      "playback_url": "https://mlb-cuts-diamond.mlb.com/FORGE/2026/2026-05/18/fbada3d8-5b21c350-900aed6e-csvm-diamondgcp-asset_1280x720_59_4000K.mp4",
      "title": "Sonny Gray's nine strikeouts"
    },
    {
      "date": "2026-05-19T01:02:46.783Z",
      "description": "Seth Lugo records five strikeouts across six strong innings of work in his start against the Red Sox",
      "duration": "00:00:47",
      "id": "seth-lugo-s-five-strikeouts-vs-red-sox",
      "image_url": "https://img.mlbstatic.com/mlb-images/image/upload/w_1920,h_1080,f_jpg,c_fill,g_auto/mlb/jaet9o12pyfngbzy7kph.jpg",
      "mlb_url": null,
      "playback_type": "mp4Avc",
      "playback_url": "https://mlb-cuts-diamond.mlb.com/FORGE/2026/2026-05/18/6de4865b-536ad254-d8cc7621-csvm-diamondgcp-asset_1280x720_59_4000K.mp4",
      "title": "Seth Lugo's five strikeouts vs. Red Sox"
    }
  ],
  "source": "mlb-stats-api"
}
