{
  "division_rank": "11.5 GB in the AL Central",
  "generated_at": "2026-06-04T07:20:16.899224+00:00",
  "headline": "A compact command center for the Royals season",
  "last_game": {
    "date": "2026-06-03",
    "opponent": "Cincinnati Reds",
    "score": "KC 5, CIN 2",
    "short_result": "W KC 5, CIN 2"
  },
  "latest_prospect_update": {
    "name": "Blake Mitchell",
    "note": "Heating Up: .208 / .375 / .625"
  },
  "next_game": {
    "date": "2026-06-04",
    "home_away": "away",
    "matchup": "Royals at Twins",
    "opponent": "Minnesota Twins",
    "probable_pitchers": {
      "opponent": {
        "id": 702193,
        "name": "Andrew Morris"
      },
      "royals": {
        "id": 607625,
        "name": "Seth Lugo"
      }
    },
    "site": "Away",
    "time_local": "7:40 PM ET",
    "venue": "Target Field"
  },
  "nightly_recap": "The Royals beat the Cincinnati Reds, KC 5, CIN 2. Stephen Kolek led the night, working 7.0 innings with 2 earned runs, 8 strikeouts and 2 walks. Michael Massey supplied the loudest Royals contact at 104.0 mph.",
  "pitcher_watch": {
    "name": "Michael Wacha",
    "reason": "Strikeout leader with 65 punchouts."
  },
  "player_of_game": {
    "name": "Stephen Kolek",
    "reason": "worked 7.0 innings with 2 earned runs, 8 strikeouts and 2 walks."
  },
  "record": {
    "games_played": 62,
    "losses": 38,
    "win_pct": 0.387,
    "wins": 24
  }
}
